CHANGELOG.md
LICENSE.txt
MANIFEST.in
README.md
pyproject.toml
setup.cfg
setup.py
pytation/__init__.py
pytation/__main__.py
pytation/analysis.py
pytation/api.py
pytation/cli_runner.py
pytation/context.py
pytation/gui_runner.py
pytation/keywords.py
pytation/loader.py
pytation/pretty_json.py
pytation/progress.py
pytation/qt_util.py
pytation/time.py
pytation/version.py
pytation.egg-info/PKG-INFO
pytation.egg-info/SOURCES.txt
pytation.egg-info/dependency_links.txt
pytation.egg-info/entry_points.txt
pytation.egg-info/requires.txt
pytation.egg-info/top_level.txt
pytation/entry_points/__init__.py
pytation/entry_points/analyze.py
pytation/entry_points/cli.py
pytation/entry_points/gui.py
pytation/test/__init__.py
pytation/test/test_01.py
pytation/test/test_analysis.py
pytation/test/test_context.py
pytation/test/test_loader.py
pytation/test/test_pretty_json.py
pytation/test/test_progress.py
pytation/test/test_time.py
pytation/test/tmodule.py
pytation_examples/__init__.py
pytation_examples/simple/__init__.py
pytation_examples/simple/station.py