Metadata-Version: 2.1
Name: pytation
Version: 0.2.4
Summary: Create manufacturing and validation tests for hardware development.
Home-page: https://github.com/jetperch/pytation
Author: Jetperch LLC
Author-email: joulescope-dev@jetperch.com
License: Apache 2.0
Project-URL: Bug Reports, https://github.com/jetperch/pytation/issues
Project-URL: Source, https://github.com/jetperch/pytation
Keywords: hardware validation manufacturing test station
Classifier: Development Status :: 5 - Production/Stable
Classifier: Intended Audience :: Developers
Classifier: Intended Audience :: End Users/Desktop
Classifier: Intended Audience :: Science/Research
Classifier: Intended Audience :: Manufacturing
Classifier: License :: OSI Approved :: Apache Software License
Classifier: Operating System :: Microsoft :: Windows :: Windows 10
Classifier: Operating System :: MacOS :: MacOS X
Classifier: Operating System :: POSIX :: Linux
Classifier: Programming Language :: Python
Classifier: Programming Language :: Python :: 3
Classifier: Programming Language :: Python :: 3.9
Classifier: Programming Language :: Python :: 3.10
Classifier: Programming Language :: Python :: 3.11
Classifier: Programming Language :: Python :: Implementation :: CPython
Classifier: Natural Language :: English
Classifier: Topic :: Scientific/Engineering
Classifier: Topic :: Software Development :: Embedded Systems
Classifier: Topic :: Software Development :: Testing
Classifier: Topic :: System :: Hardware
Classifier: Topic :: Utilities
Requires-Python: ~=3.9
License-File: LICENSE.txt
